hkopenai/hk_transportation_mcp_server/__init__.py
hkopenai/hk_transportation_mcp_server/__main__.py
hkopenai/hk_transportation_mcp_server/server.py
iflow_mcp_hkopenai_hk_transportation_mcp_server-0.2.8.dist-info/licenses/LICENSE
iflow_mcp_hkopenai_hk_transportation_mcp_server-0.2.8.dist-info/METADATA
iflow_mcp_hkopenai_hk_transportation_mcp_server-0.2.8.dist-info/WHEEL
iflow_mcp_hkopenai_hk_transportation_mcp_server-0.2.8.dist-info/entry_points.txt
iflow_mcp_hkopenai_hk_transportation_mcp_server-0.2.8.dist-info/top_level.txt
iflow_mcp_hkopenai_hk_transportation_mcp_server-0.2.8.dist-info/RECORD
