Metadata-Version: 2.4
Name: iflow-mcp_hkopenai.hk_transportation_mcp_server
Version: 0.2.8
Summary: Hong Kong transportation MCP Server providing transportation data tools
Author-email: Neo Chow <neo@01man.com>
License-Expression: MIT
Project-URL: repository, https://github.com/hkopenai/hk-transportation-mcp-server.git
Classifier: Programming Language :: Python :: 3
Classifier: Operating System :: OS Independent
Requires-Python: >=3.7
License-File: LICENSE
Requires-Dist: fastmcp>=2.10.2
Requires-Dist: requests>=2.31.0
Requires-Dist: pytest>=8.2.0
Requires-Dist: pytest-cov>=6.1.1
Requires-Dist: modelcontextprotocol
Requires-Dist: hkopenai_common>=0.3.0
Dynamic: license-file
